brbitcoin/__init__.py
brbitcoin-0.1.0.dist-info/METADATA
brbitcoin-0.1.0.dist-info/WHEEL
brbitcoin-0.1.0.dist-info/RECORD
